uipath/py.typed
uipath/_cli/README.md
uipath/_cli/__init__.py
uipath/_cli/cli_add.py
uipath/_cli/cli_auth.py
uipath/_cli/cli_debug.py
uipath/_cli/cli_deploy.py
uipath/_cli/cli_dev.py
uipath/_cli/cli_eval.py
uipath/_cli/cli_init.py
uipath/_cli/cli_invoke.py
uipath/_cli/cli_new.py
uipath/_cli/cli_pack.py
uipath/_cli/cli_publish.py
uipath/_cli/cli_pull.py
uipath/_cli/cli_push.py
uipath/_cli/cli_register.py
uipath/_cli/cli_run.py
uipath/_cli/middlewares.py
uipath/_cli/runtimes.py
uipath/_cli/spinner.py
uipath/_cli/_auth/_auth_server.py
uipath/_cli/_auth/_auth_service.py
uipath/_cli/_auth/_models.py
uipath/_cli/_auth/_oidc_utils.py
uipath/_cli/_auth/_portal_service.py
uipath/_cli/_auth/_url_utils.py
uipath/_cli/_auth/_utils.py
uipath/_cli/_auth/auth_config_25_10.json
uipath/_cli/_auth/auth_config_cloud.json
uipath/_cli/_auth/index.html
uipath/_cli/_auth/localhost.crt
uipath/_cli/_auth/localhost.key
uipath/_cli/_chat/_bridge.py
uipath/_cli/_debug/_bridge.py
uipath/_cli/_evals/__init__.py
uipath/_cli/_evals/_configurable_factory.py
uipath/_cli/_evals/_console_progress_reporter.py
uipath/_cli/_evals/_eval_util.py
uipath/_cli/_evals/_evaluate.py
uipath/_cli/_evals/_evaluator_factory.py
uipath/_cli/_evals/_helpers.py
uipath/_cli/_evals/_progress_reporter.py
uipath/_cli/_evals/_runtime.py
uipath/_cli/_evals/_span_collection.py
uipath/_cli/_evals/_span_utils.py
uipath/_cli/_evals/_telemetry.py
uipath/_cli/_evals/_models/_evaluation_set.py
uipath/_cli/_evals/_models/_evaluator.py
uipath/_cli/_evals/_models/_evaluator_base_params.py
uipath/_cli/_evals/_models/_exceptions.py
uipath/_cli/_evals/_models/_mocks.py
uipath/_cli/_evals/_models/_output.py
uipath/_cli/_evals/_models/_sw_reporting.py
uipath/_cli/_evals/mocks/__init__.py
uipath/_cli/_evals/mocks/cache_manager.py
uipath/_cli/_evals/mocks/input_mocker.py
uipath/_cli/_evals/mocks/llm_mocker.py
uipath/_cli/_evals/mocks/mocker.py
uipath/_cli/_evals/mocks/mocker_factory.py
uipath/_cli/_evals/mocks/mockito_mocker.py
uipath-2.5.2.dist-info/METADATA
uipath-2.5.2.dist-info/WHEEL
uipath-2.5.2.dist-info/entry_points.txt
uipath-2.5.2.dist-info/licenses/LICENSE
uipath-2.5.2.dist-info/RECORD
