Metadata-Version: 2.4
Name: uipath
Version: 2.5.2
Summary: Python SDK and CLI for UiPath Platform, enabling programmatic interaction with automation services, process management, and deployment tools.
Project-URL: Homepage, https://uipath.com
Project-URL: Repository, https://github.com/UiPath/uipath-python
Project-URL: Documentation, https://uipath.github.io/uipath-python/
Maintainer-email: Marius Cosareanu <marius.cosareanu@uipath.com>, Cristian Pufu <cristian.pufu@uipath.com>
License-File: LICENSE
Classifier: Intended Audience :: Developers
Classifier: Programming Language :: Python :: 3.11
Classifier: Programming Language :: Python :: 3.12
Classifier: Programming Language :: Python :: 3.13
Classifier: Topic :: Software Development :: Build Tools
Requires-Python: >=3.11
Requires-Dist: applicationinsights>=0.11.10
Requires-Dist: click>=8.3.1
Requires-Dist: coverage>=7.8.2
Requires-Dist: httpx>=0.28.1
Requires-Dist: mermaid-builder==0.0.3
Requires-Dist: mockito>=1.5.4
Requires-Dist: pathlib>=1.0.1
Requires-Dist: pydantic-function-models>=0.1.11
Requires-Dist: pyjwt>=2.10.1
Requires-Dist: pysignalr==1.3.0
Requires-Dist: python-dotenv>=1.0.1
Requires-Dist: python-socketio<6.0.0,>=5.15.0
Requires-Dist: rich>=14.2.0
Requires-Dist: tenacity>=9.0.0
Requires-Dist: truststore>=0.10.1
Requires-Dist: uipath-core<0.2.0,>=0.1.6
Requires-Dist: uipath-runtime<0.6.0,>=0.5.0
